.DS_Store
TrainModule/Evaluation.py
TrainModule/Experiment.py
TrainModule/Trainer.py
TrainModule/__init__.py
TrainModule/backup.py
TrainModule/checkpoint.py
TrainModule/progress.py
wgk_torch_training_module-1.1.dist-info/METADATA
wgk_torch_training_module-1.1.dist-info/WHEEL
wgk_torch_training_module-1.1.dist-info/top_level.txt
wgk_torch_training_module-1.1.dist-info/RECORD
