Metadata-Version: 2.1
Name: wgk-torch-training-module
Version: 1.1
Summary: wgk torch training module
Author: WonGook
Author-email: onlyworld94@naver.com
Classifier: Programming Language :: Python :: 3
Classifier: License :: OSI Approved :: MIT License
Classifier: Operating System :: OS Independent
Requires-Python: >=3.8
